COPYING
README.md
pyproject.toml
setup.py
pathrs/__init__.py
pathrs/_internal.py
pathrs/_pathrs.py
pathrs/pathrs_build.py
pathrs/procfs.py
pathrs/py.typed
pathrs.egg-info/PKG-INFO
pathrs.egg-info/SOURCES.txt
pathrs.egg-info/dependency_links.txt
pathrs.egg-info/requires.txt
pathrs.egg-info/top_level.txt
pathrs/_libpathrs_cffi/__init__.pyi
pathrs/_libpathrs_cffi/lib.pyi