Metadata-Version: 2.4
Name: pathrs
Version: 0.2.3
Summary: Python bindings for libpathrs, a safe path resolution library for Linux.
Author-email: Aleksa Sarai <cyphar@cyphar.com>
Maintainer-email: Aleksa Sarai <cyphar@cyphar.com>
License-Expression: MPL-2.0
Project-URL: Homepage, https://github.com/cyphar/libpathrs
Project-URL: Repository, https://github.com/cyphar/libpathrs
Project-URL: Documentation, https://docs.rs/pathrs
Project-URL: Changelog, https://github.com/cyphar/libpathrs/blob/main/CHANGELOG.md
Keywords: libpathrs,pathrs
Platform: Linux
Classifier: Topic :: Security
Classifier: Topic :: System :: Filesystems
Classifier: Intended Audience :: Developers
Classifier: Natural Language :: English
Classifier: Operating System :: POSIX :: Linux
Classifier: Programming Language :: Python
Classifier: Programming Language :: Python :: 3
Classifier: Topic :: Software Development :: Libraries :: Python Modules
Requires-Python: >=3.9
License-File: COPYING
Requires-Dist: cffi>=1.10.0
Requires-Dist: typing_extensions>=4.0.0
Dynamic: license-file
Dynamic: platform
